{"stats":{"minecraft:dropped":{"malum:wicked_spirit":2,"minecraft:lapis_lazuli":15,"regions_unexplored:dead_planks":3,"minecraft:glass_bottle":4,"minecraft:diamond":3,"minecraft:crossbow":1,"blue_skies:briskbloom":2,"minecraft:orange_tulip":1,"minecraft:cracked_stone_bricks":1,"irons_spellbooks:tarnished_helmet":1,"minecraft:leather_helmet":2,"farmersdelight:beef_patty":1,"minecraft:item_frame":2,"minecraft:emerald":4,"minecraft:dirt":2484,"beachparty:overgrown_disc":1,"minecraft:stone_button":6,"beachparty:rubber_ring_pelican":2,"minecraft:chain":11,"minecraft:gold_nugget":38,"irons_spellbooks:gold_spell_book":1,"minecraft:bone_meal":1,"regions_unexplored:prismarite_cluster":2,"minecraft:iron_pickaxe":1,"minecraft:sugar":6,"blue_skies:glimmer_reed":14,"minecraft:white_wool":1,"regions_unexplored:cave_hyssop":1,"minecraft:bone":21,"minecraft:stone_axe":1,"blue_skies:bug_guts":5,"minecraft:iron_nugget":57,"minecraft:golden_chestplate":1,"minecraft:cobbled_deepslate":195,"blue_skies:pyrope_shovel":1,"alexscaves:cave_tablet":6,"minecraft:wheat":34,"minecraft:rotten_flesh":150,"supplementaries:flax_seeds":5,"nethers_exorcism:indigo_roots":1,"irons_spellbooks:cooldown_ring":2,"regions_unexplored:hanging_prismarite":1,"farmersdelight:rope":6,"minecraft:leather_leggings":2,"minecraft:beef":2,"blue_skies:starlit_planks":2,"blue_skies:pyrope_gem":3,"minecraft:egg":2,"farmersdelight:tomato_seeds":12,"minecraft:golden_boots":2,"blue_skies:pyrope_boots":1,"regions_unexplored:fireweed":4,"minecraft:wheat_seeds":45,"minecraft:oak_fence":2,"minecraft:iron_helmet":1,"minecraft:cobblestone":10,"minecraft:book":2,"blue_skies:aquite_axe":3,"blue_skies:lunar_dirt":2,"minecraft:apple":5,"minecraft:granite":9,"minecraft:golden_apple":1,"minecraft:coal":40,"regions_unexplored:daisy":1,"blue_skies:bluebright_planks":2,"blue_skies:turquoise_stone_axe":1,"minecraft:cobweb":4,"minecraft:golden_carrot":9,"regions_unexplored:purple_lupine":13,"regions_unexplored:glistering_sprout":12,"minecraft:potion":4,"minecraft:white_banner":1,"minecraft:iron_shovel":1,"minecraft:paper":2,"minecraft:string":33,"hexerei:sage_seed":6,"minecraft:stone_sword":1,"minecraft:cocoa_beans":6,"minecraft:bowl":2,"minecraft:chicken":1,"regions_unexplored:clover":1860,"minecraft:clay_ball":4,"minecraft:cherry_slab":1,"minecraft:name_tag":1,"minecraft:big_dripleaf":7,"minecraft:hay_block":8,"minecraft:potato":9,"minecraft:cobblestone_slab":4,"botania:lexicon":1,"minecraft:diamond_pickaxe":4,"blue_skies:pyrope_pickaxe":1,"regions_unexplored:white_magnolia_shrub":2,"minecraft:spider_eye":4,"minecraft:stone_bricks":1,"regions_unexplored:glistering_fern":2,"minecraft:bow":5,"minecraft:magma_block":1,"regions_unexplored:blue_lupine":6,"regions_unexplored:cobalt_roots":1,"minecraft:moss_block":2,"minecraft:golden_pickaxe":1,"malum:earthen_spirit":3,"regions_unexplored:glister_spire":1,"botania:red_mushroom":1,"minecraft:leather":3,"blue_skies:aquite_sword":3,"minecraft:iron_horse_armor":2,"blue_skies:umber":4,"minecraft:flint":5,"minecraft:music_disc_13":2,"alexscaves:galena":5,"blue_skies:turquoise_stone_pickaxe":1,"minecraft:brush":1,"blue_skies:turquoise_cobblestone":103,"minecraft:mutton":1,"regions_unexplored:glistering_ivy":2,"alexscaves:ferrouslime_ball":1,"regions_unexplored:felicia_daisy":1,"nethers_exorcism:indigo_leaves":5,"vinery:red_grape_seeds":3,"minecraft:gravel":13,"minecraft:spyglass":1,"blue_skies:dusk_stick":2,"regions_unexplored:mycotoxic_grass":2,"minecraft:leather_chestplate":1,"supplementaries:ash":64,"minecraft:gunpowder":20,"minecraft:melon_seeds":5,"minecraft:chest":2,"doggytalents:rice_grains":8,"minecraft:basalt":8,"minecraft:arrow":20,"minecraft:netherrack":6,"minecraft:firework_rocket":1,"minecraft:bread":7,"minecraft:mossy_cobblestone":4,"hexerei:mahogany_log":6,"alexscaves:spelunkery_table":1,"regions_unexplored:yellow_lupine":1,"regions_unexplored:pine_sapling":1,"blue_skies:lunar_stick":6,"minecraft:tropical_fish":1,"minecraft:stick":240,"irons_spellbooks:scroll":1,"mca:book_romance":1,"irons_spellbooks:affinity_ring":1,"minecraft:milk_bucket":1,"minecraft:torch":9,"minecraft:map":2,"blue_skies:turquoise_stone_sword":1,"minecraft:iron_leggings":1,"regions_unexplored:dead_steppe_shrub":1,"minecraft:iron_axe":3,"minecraft:tripwire_hook":1,"minecraft:bucket":1,"minecraft:music_disc_cat":1,"minecraft:smooth_basalt":5,"minecraft:redstone":1,"blue_skies:brumble":1,"relics:hunter_belt":1,"betterarcheology:artifact_shards":1,"minecraft:tuff":14,"minecraft:raw_iron":77,"farmersdelight:cabbage_seeds":1,"regions_unexplored:joshua_log":1,"minecraft:iron_hoe":1,"blue_skies:moonstone_shard":1,"regions_unexplored:pink_lupine":10,"botania:pink_mushroom":1,"blue_skies:bluebright_stick":2,"farmersdelight:flint_knife":1,"malum:crude_scythe":2,"minecraft:iron_chestplate":1,"minecraft:andesite":60,"blue_skies:fiery_bean_seeds":1,"botania:mana_bottle":1,"blue_skies:pyrope_sword":1,"minecraft:stone_pickaxe":1,"minecraft:wooden_pickaxe":2,"minecraft:calcite":3},"minecraft:killed":{"minecraft:cave_spider":5,"alexscaves:boundroid":3,"blue_skies:frost_spirit":1,"minecraft:skeleton":47,"blue_skies:diophyde_prowler":1,"irons_spellbooks:apothecarist":1,"minecraft:chicken":1,"minecraft:skeleton_horse":2,"alexscaves:teletor":2,"minecraft:magma_cube":3,"goblins_tyranny:mini_goblin_2":2,"minecraft:pillager":21,"minecraft:zombie":243,"minecraft:glow_squid":2,"minecraft:cow":2,"mca:male_zombie_villager":1,"minecraft:endermite":3,"minecraft:vindicator":4,"alexscaves:ferrouslime":1,"minecraft:horse":1,"brazil_legends:capelobo":4,"goblins_tyranny:mini_goblin_1":1,"blue_skies:nyctofly":7,"minecraft:husk":2,"irons_spellbooks:citadel_keeper":1,"minecraft:frog":1,"minecraft:enderman":5,"blue_skies:armored_frost_spirit":9,"minecraft:witch":4,"minecraft:spider":28,"blue_skies:venom_spider":4,"blue_skies:whistleshell_crab":1,"grimoireofgaia:minotaurus":1,"quark:forgotten":4,"blue_skies:crynocerous":1,"minecraft:silverfish":3,"blue_skies:emberback":2,"minecraft:piglin_brute":1,"irons_spellbooks:summoned_skeleton":2,"blue_skies:shrumpty":1,"alexscaves:notor":1,"irons_spellbooks:necromancer":4,"minecraft:creeper":11,"minecraft:sheep":2,"minecraft:ghast":1,"grimoireofgaia:harpy":2,"irons_spellbooks:summoned_zombie":7,"grimoireofgaia:satyress":2,"grimoireofgaia:succubus":1,"minecraft:slime":13,"nethers_exorcism:chroma_lurker":2,"blue_skies:shade_monitor":2,"quark:foxhound":2,"takesapillage:skirmisher":1,"minecraft:bat":2,"minecraft:hoglin":7,"grimoireofgaia:oni":1,"blue_skies:stardust_ram":1,"minecraft:wither_skeleton":1},"minecraft:crafted":{"minecraft:smooth_stone":3,"regions_unexplored:maple_planks":8,"hexerei:mahogany_planks":8,"minecraft:cracked_stone_bricks":42,"minecraft:cooked_mutton":5,"botania:red_petal":2,"blue_skies:maple_planks":4,"minecraft:glass":8,"hexerei:willow_slab":6,"hexerei:witch_hazel_stairs":16,"blue_skies:aquite_pickaxe":2,"minecraft:decorated_pot":3,"blue_skies:dusk_stick":4,"blue_skies:starlit_stick":64,"blue_skies:pyrope_sword":1,"regions_unexplored:palm_planks":4,"blue_skies:blue_journal":1,"malum:encyclopedia_arcana":1,"regions_unexplored:yellow_bioshroom_planks":12,"hexerei:book_of_shadows":1,"blue_skies:aquite_sword":1,"minecraft:copper_ingot":15,"minecraft:hay_block":55,"minecraft:campfire":1,"minecraft:painting":1,"blue_skies:pyrope_axe":1,"blue_skies:bluebright_crafting_table":3,"hexerei:willow_altar":1,"minecraft:lectern":1,"naturescompass:naturescompass":1,"blue_skies:pyrope_pickaxe":1,"hexerei:willow_planks":12,"quark:oak_chest":4,"minecraft:compass":1,"blue_skies:aquite_boots":1,"minecraft:iron_pickaxe":1,"minecraft:iron_block":6,"minecraft:gold_ingot":68,"minecraft:composter":5,"regions_unexplored:dead_wood":9,"hexerei:witch_hazel_slab":12,"blue_skies:bluebright_planks":24,"minecraft:spyglass":2,"regions_unexplored:cypress_planks":4,"quark:jungle_chest":2,"nethers_exorcism:indigo_planks":4,"minecraft:bone_meal":198,"quark:cherry_bookshelf":1,"regions_unexplored:mauve_planks":4,"malum:processed_soulstone":4,"blue_skies:turquoise_stone_sword":1,"minecraft:stone_pickaxe":1,"regions_unexplored:willow_slab":6,"minecraft:dark_oak_planks":116,"regions_unexplored:magnolia_planks":48,"irons_spellbooks:gold_spell_book":1,"minecraft:wheat":1179,"minecraft:enchanting_table":1,"botania:lexicon":1,"regions_unexplored:dead_planks":200,"minecraft:glowstone":4,"regions_unexplored:eucalyptus_planks":4,"regions_unexplored:socotra_planks":4,"regions_unexplored:pine_planks":4,"hexerei:witch_hazel_trapdoor":8,"minecraft:iron_shovel":11,"minecraft:iron_leggings":4,"blue_skies:starlit_planks":72,"regions_unexplored:dead_pine_sapling":2,"minecraft:brick":48,"regions_unexplored:baobab_planks":8,"minecraft:oak_planks":68,"minecraft:barrel":18,"minecraft:cherry_slab":48,"blue_skies:turquoise_stone_pickaxe":1,"minecraft:stone":612,"minecraft:cherry_boat":1,"regions_unexplored:larch_planks":4,"nethers_exorcism:cooked_lurker_meat":8,"quark:cherry_chest":14,"regions_unexplored:kapok_planks":4,"blue_skies:aquite":13,"irons_spellbooks:alchemist_cauldron":1,"nethersdelight:hoglin_sirloin":13,"blue_skies:aquite_helmet":1,"minecraft:bow":1,"minecraft:iron_boots":2,"regions_unexplored:brimwood_planks":4,"regions_unexplored:cobalt_planks":4,"regions_unexplored:willow_planks":44,"stalwart_dungeons:iron_hammer":1,"minecraft:stone_bricks":480,"call_of_yucutan:macuahuitl":1,"minecraft:item_frame":12,"quark:blossom_planks":4,"blue_skies:aquite_leggings":1,"minecraft:cauldron":1,"beachparty:mini_fridge":1,"blue_skies:dusk_planks":4,"minecraft:crafting_table":10,"regions_unexplored:dead_stairs":120,"minecraft:wooden_pickaxe":1,"minecraft:iron_helmet":1,"minecraft:baked_potato":62,"minecraft:brush":1,"minecraft:red_wool":2,"blue_skies:aquite_axe":2,"minecraft:gold_block":1,"minecraft:birch_planks":4,"minecraft:dark_oak_slab":54,"minecraft:iron_chestplate":2,"minecraft:paper":93,"minecraft:diamond_pickaxe":1,"minecraft:shield":1,"minecraft:stick":292,"regions_unexplored:socotra_sapling":4,"minecraft:iron_ingot":171,"minecraft:stone_sword":1,"regions_unexplored:dead_slab":6,"minecraft:shears":2,"blue_skies:aquite_shovel":3,"blue_skies:turquoise_stone_axe":1,"minecraft:cherry_planks":340,"malum:runewood_planks":56,"minecraft:coal":99,"minecraft:mossy_stone_bricks":38,"minecraft:furnace":6,"blue_skies:zeal_lighter":1,"minecraft:cherry_sapling":4,"blue_skies:lunar_stone_pickaxe":1,"alexscaves:cave_map":1,"minecraft:flint_and_steel":2,"minecraft:scaffolding":42,"irons_spellbooks:scroll_forge":1,"regions_unexplored:joshua_planks":652,"minecraft:polished_deepslate":4,"minecraft:iron_axe":13,"minecraft:iron_hoe":1,"doggytalents:giant_stick":1,"relics:researching_table":1,"malum:crude_scythe":1,"blue_skies:pyrope_shovel":7,"hexerei:witch_hazel_fence":15,"irons_spellbooks:blood_rune":1,"blue_skies:pyrope_boots":1,"beachparty:palm_planks":4,"minecraft:red_dye":2,"hexerei:witch_hazel_planks":92,"hexerei:witch_hazel_door":3,"minecraft:bucket":1,"minecraft:stone_axe":1,"minecraft:air":0,"minecraft:bread":237,"minecraft:jungle_planks":20,"minecraft:blue_dye":1,"blue_skies:bluebright_stick":12,"minecraft:anvil":2,"minecraft:acacia_planks":8,"minecraft:torch":396,"minecraft:firework_rocket":69},"minecraft:mined":{"regions_unexplored:yellow_bioshroom_block":66,"quark:azalea_log":8,"regions_unexplored:blue_lupine":6,"irons_spellbooks:armor_pile":1,"minecraft:cherry_log":192,"regions_unexplored:magnolia_log":12,"alexscaves:azure_neodymium_pillar":54,"minecraft:obsidian":26,"regions_unexplored:brimwood_leaves":245,"minecraft:carved_pumpkin":1,"regions_unexplored:kapok_log":50,"regions_unexplored:cattail":8,"minecraft:granite":9,"minecraft:acacia_log":2,"minecraft:jungle_log":15,"blue_skies:everbright_aquite_ore":13,"minecraft:coal_block":11,"hexerei:witch_hazel_fence":2,"blue_skies:snowcap_mushroom":3,"blue_skies:stripped_starlit_log":1,"regions_unexplored:blue_bioshroom":1,"minecraft:spawner":1,"regions_unexplored:birch_branch":1,"minecraft:polished_blackstone_bricks":1,"minecraft:magma_block":2,"regions_unexplored:stone_bud":2,"nethers_exorcism:indigo_leaves":5,"minecraft:cobbled_deepslate":14,"minecraft:barrel":1,"minecraft:fire":10,"malum:natural_quartz_ore":17,"minecraft:moss_carpet":4,"minecraft:deepslate_lapis_ore":5,"nethers_exorcism:indigo_nylium":4,"minecraft:fletching_table":1,"alexscaves:scarlet_neodymium_node":3,"regions_unexplored:pine_leaves":10,"hexerei:mahogany_log":108,"minecraft:cave_vines":2,"minecraft:water_cauldron":1,"minecraft:dirt_path":13,"minecraft:oak_stairs":1,"minecraft:pink_tulip":1,"blue_skies:dusk_log":27,"betterarcheology:rotten_trapdoor":2,"regions_unexplored:prismoss":1,"minecraft:tripwire":3,"goblins_tyranny:shaman_skull":4,"regions_unexplored:dead_steppe_shrub":1,"blue_skies:turquoise_stonebrick":18,"minecraft:smoker":2,"regions_unexplored:duckweed":1,"minecraft:amethyst_cluster":3,"minecraft:piglin_head":1,"betterarcheology:rotten_slab":1,"minecraft:torch":79,"regions_unexplored:glowing_yellow_bioshroom_block":6,"vinery:red_grape_bush":1,"blue_skies:lunar_grass_block":1,"minecraft:polished_andesite_stairs":3,"minecraft:dead_bush":2,"malum:brilliant_deepslate":9,"alexscaves:energized_galena_scarlet":3,"quark:blossom_log":48,"blue_skies:bluebright_crafting_table":2,"regions_unexplored:cobalt_roots":1,"blue_skies:maple_log":65,"minecraft:sugar_cane":115,"blue_skies:lunar_stone":3,"regions_unexplored:pine_log":43,"minecraft:amethyst_block":2,"regions_unexplored:hyssop":2,"regions_unexplored:glister_bulb":6,"nethers_exorcism:indigo_fruit":3,"blue_skies:moonlit_bloom":1,"betterarcheology:rotten_planks":1,"minecraft:grass":49,"regions_unexplored:eucalyptus_log":57,"regions_unexplored:bamboo_leaves":2,"blue_skies:brittlebush":2,"regions_unexplored:clover":162,"regions_unexplored:glistering_ivy":3,"minecraft:smooth_basalt":5,"minecraft:deepslate":343,"regions_unexplored:glistering_sprout":26,"regions_unexplored:mycotoxic_grass":2,"regions_unexplored:fireweed":5,"regions_unexplored:spruce_shrub":1,"minecraft:mossy_cobblestone":23,"blue_skies:umber":4,"botania:red_mushroom":1,"minecraft:dark_oak_log":47,"minecraft:spruce_fence":1,"regions_unexplored:saguaro_cactus":2,"steam_powered:tin_ore":12,"regions_unexplored:dead_log":263,"minecraft:moss_block":81,"alexscaves:galena":16,"blue_skies:moonlit_water_lily":13,"steam_powered:zinc_ore":7,"regions_unexplored:socotra_leaves":1,"farmersdelight:wild_onions":1,"minecraft:packed_mud":1,"blue_skies:maple_sapling":1,"minecraft:andesite":97,"regions_unexplored:stripped_dead_wood":7,"hexerei:witch_hazel_log":29,"regions_unexplored:larch_leaves":23,"regions_unexplored:dead_stairs":11,"minecraft:big_dripleaf_stem":1,"blue_skies:crescent_fruit":16,"minecraft:cobblestone_slab":5,"minecraft:vine":7,"blue_skies:chillweed":1,"regions_unexplored:apple_oak_leaves":2,"regions_unexplored:ash_vent":20,"minecraft:bamboo":18,"irons_spellbooks:inscription_table":3,"regions_unexplored:windswept_grass":2,"regions_unexplored:felicia_daisy":2,"alexscaves:tesla_bulb":1,"hexerei:flowering_lily_pad":1,"regions_unexplored:cypress_log":10,"minecraft:cherry_planks":4,"minecraft:hanging_roots":1,"alexscaves:azure_neodymium_node":7,"betterarcheology:growth_totem":1,"blue_skies:starlit_log":36,"blue_skies:warding_pearl":1,"minecraft:emerald_ore":1,"regions_unexplored:salmon_poppy_bush":1,"botania:pink_mushroom":1,"blue_skies:briskbloom":2,"minecraft:copper_ore":9,"minecraft:tall_grass":13,"regions_unexplored:mauve_log":13,"farmersdelight:wild_tomatoes":3,"minecraft:deepslate_gold_ore":77,"blue_skies:snowcap_mushroom_block":1,"minecraft:diorite":1,"regions_unexplored:prismarite_cluster":15,"minecraft:coarse_dirt":2,"blue_skies:starlit_planks":2,"blue_skies:turquoise_grass_block":1,"minecraft:light_blue_bed":13,"betterarcheology:loot_vase_creeper":9,"regions_unexplored:steppe_shrub":1,"blue_skies:glimmer_reed":79,"regions_unexplored:magnolia_shrub":1,"regions_unexplored:silver_birch_log":28,"minecraft:gravel":34,"hexerei:witch_hazel_trapdoor":15,"minecraft:cobweb":2,"hexerei:willow_vines_plant":2,"minecraft:stone_bricks":105,"malum:runewood_log":103,"regions_unexplored:magnolia_planks":1,"minecraft:fern":8,"nethers_exorcism:indigo_roots":1,"regions_unexplored:golden_larch_leaves":3,"minecraft:stone_pressure_plate":1,"regions_unexplored:dead_pine_shrub":2,"vinery:apple_tree_sapling":1,"quark:cherry_chest":1,"blue_skies:muckweed":4,"regions_unexplored:maple_log":19,"blue_skies:bluebright_leaves":4,"hexerei:stripped_willow_log":3,"minecraft:cobblestone_stairs":1,"blue_skies:snowcap_pinhead":1,"regions_unexplored:pink_magnolia_shrub":1,"regions_unexplored:hanging_prismarite":2,"malum:soulstone_ore":2,"minecraft:cave_vines_plant":1,"regions_unexplored:yellow_bioshroom_stem":13,"minecraft:grass_block":2242,"farmersdelight:budding_tomatoes":1,"regions_unexplored:elephant_ear":1,"vinery:apple_log":44,"regions_unexplored:small_oak_leaves":3,"irons_spellbooks:scroll_forge":1,"minecraft:glowstone":6,"malum:blazing_quartz_ore":5,"minecraft:iron_ore":72,"regions_unexplored:glister_spire":5,"regions_unexplored:purple_lupine":9,"blue_skies:lunar_stonebrick":13,"botania:green_mushroom":1,"minecraft:skeleton_wall_skull":1,"minecraft:flowering_azalea_leaves":2,"regions_unexplored:stripped_dead_log":111,"minecraft:azalea_leaves":9,"minecraft:azalea":1,"regions_unexplored:larch_log":67,"minecraft:deepslate_redstone_ore":12,"hexerei:herb_drying_rack":2,"blue_skies:turquoise_stone":81,"regions_unexplored:willow_log":12,"minecraft:blackstone":72,"betterarcheology:rotten_log":7,"blue_skies:midnight_sand":1,"malum:cthonic_gold_ore":9,"minecraft:clay":17,"malum:cthonic_gold_cluster":7,"alexscaves:energized_galena_neutral":1,"minecraft:calcite":3,"minecraft:chest":2,"regions_unexplored:small_desert_shrub":3,"nethers_exorcism:indigo_log":52,"minecraft:cobblestone":78,"blue_skies:lunar_grass":21,"minecraft:grindstone":1,"minecraft:oak_planks":1,"regions_unexplored:bamboo_log":14,"minecraft:wall_torch":85,"minecraft:deepslate_copper_ore":1,"regions_unexplored:socotra_log":24,"minecraft:birch_log":5,"regions_unexplored:dead_slab":1,"blue_skies:bluebright_sapling":1,"beachparty:palm_log":27,"regions_unexplored:joshua_log":389,"regions_unexplored:cherry_shrub":2,"minecraft:oak_log":25,"minecraft:beetroots":1,"regions_unexplored:peat_dirt":3,"minecraft:sand":9,"minecraft:dirt":2483,"hexerei:witch_hazel_slab":4,"minecraft:tripwire_hook":2,"minecraft:dispenser":1,"minecraft:netherrack":30,"regions_unexplored:prismoss_sprout":5,"hexerei:willow_log":27,"minecraft:oak_leaves":4,"blue_skies:everbright_pyrope_ore":22,"minecraft:nether_gold_ore":8,"minecraft:crying_obsidian":4,"alexscaves:spelunkery_table":1,"minecraft:tuff":22,"minecraft:deepslate_diamond_ore":6,"minecraft:candle":15,"regions_unexplored:pink_lupine":8,"regions_unexplored:glistering_fern":3,"minecraft:decorated_pot":5,"regions_unexplored:silver_birch_shrub":1,"botania:orange_mushroom":1,"minecraft:brown_mushroom_block":2,"betterarcheology:cracked_mud_bricks":2,"farmersdelight:tomatoes":1,"regions_unexplored:large_prismarite_cluster":2,"malum:natural_quartz_cluster":2,"regions_unexplored:cobalt_log":8,"minecraft:large_fern":1,"malum:exposed_runewood_log":4,"blue_skies:crescent_fruit_leaves":1,"minecraft:hay_block":129,"regions_unexplored:brimwood_log_magma":3,"regions_unexplored:baobab_log":28,"minecraft:spore_blossom":1,"regions_unexplored:dead_sapling":5,"minecraft:oak_trapdoor":1,"minecraft:furnace":7,"minecraft:raw_gold_block":10,"hexerei:mahogany_sapling":5,"botania:white_mushroom":1,"blue_skies:everbright_moonstone_ore":56,"regions_unexplored:white_magnolia_shrub":2,"minecraft:bookshelf":21,"minecraft:shroomlight":12,"minecraft:deepslate_iron_ore":34,"blue_skies:turquoise_dripstone":1,"regions_unexplored:medium_grass":57,"regions_unexplored:joshua_planks":498,"minecraft:stone":1202,"blue_skies:everdawn_aquite_ore":1,"blue_skies:tall_turquoise_grass":4,"minecraft:podzol":16,"doggytalents:rice_crop":2,"regions_unexplored:ashen_log":20,"supplementaries:book_pile_horizontal":1,"minecraft:scaffolding":1,"minecraft:flowering_azalea":1,"minecraft:infested_stone_bricks":1,"blue_skies:turquoise_grass":6,"regions_unexplored:brimwood_log":29,"minecraft:polished_granite":1,"regions_unexplored:mycotoxic_moss":2,"minecraft:basalt":77,"minecraft:oak_fence":3,"minecraft:crafting_table":2,"botania:yellow_double_flower":1,"hexerei:willow_altar":4,"alexscaves:metal_swarf":62,"regions_unexplored:dead_pine_sapling":6,"regions_unexplored:daisy":1,"blue_skies:star_flare":1,"supplementaries:urn":42,"nethers_exorcism:indigo_fungus":1,"regions_unexplored:yellow_bioshroom_planks":1,"regions_unexplored:socotra_shrub":2,"alexscaves:galena_iron_ore":67,"minecraft:gray_bed":3,"minecraft:white_wall_banner":1,"minecraft:yellow_bed":2,"betterarcheology:loot_vase_green":7,"hexerei:witch_hazel_stairs":2,"beachparty:mini_fridge":1,"minecraft:coal_ore":68,"minecraft:cocoa":2,"blue_skies:bluebright_log":34,"betterarcheology:evoker_trap":1,"blue_skies:turquoise_dirt":5,"regions_unexplored:palm_log":15,"nethers_exorcism:dna_vines":17,"minecraft:cracked_stone_bricks":5,"regions_unexplored:glistering_ivy_plant":1,"minecraft:polished_andesite":2,"minecraft:small_dripleaf":2,"blue_skies:tall_lunar_grass":20,"minecraft:mossy_stone_bricks":7,"alexscaves:scarlet_neodymium_pillar":57},"minecraft:used":{"irons_spellbooks:inscription_table":2,"regions_unexplored:pine_planks":1,"minecraft:moss_block":3,"grimoireofgaia:fireshard":2,"minecraft:writable_book":4,"regions_unexplored:mauve_log":2,"blue_skies:aquite_leggings":1,"hexerei:witch_hazel_log":2,"farmersdelight:cabbage_seeds":4,"malum:runewood_planks":1,"goblins_tyranny:shaman_skull":4,"hexerei:witch_hazel_planks":1,"regions_unexplored:ashen_log":2,"minecraft:rotten_flesh":2,"quark:cherry_chest":15,"blue_skies:star_flare":1,"blue_skies:pyrope_shovel":1380,"minecraft:allium":2,"blue_skies:lunar_stone_pickaxe":1,"hexerei:mahogany_sapling":6,"minecraft:lava_bucket":6,"minecraft:grass_block":2,"blue_skies:maple_sapling":2,"blue_skies:aquite_pickaxe":536,"minecraft:bow":130,"minecraft:furnace":11,"supplementaries:ash":5,"minecraft:oak_sapling":2,"minecraft:egg":2,"minecraft:potato":9,"nethers_exorcism:indigo_fruit_food":1,"regions_unexplored:silver_birch_log":2,"minecraft:mossy_stone_bricks":40,"botania:gray_mystical_flower":2,"minecraft:blackstone":3,"alexscaves:scarlet_neodymium_pillar":45,"minecraft:leather_chestplate":1,"minecraft:wooden_pickaxe":3,"minecraft:composter":4,"regions_unexplored:stripped_dead_log":109,"blue_skies:turquoise_stonebrick":14,"minecraft:golden_apple":2,"minecraft:glow_berries":2,"regions_unexplored:dead_log":138,"regions_unexplored:pine_sapling":4,"blue_skies:brewberry":4,"regions_unexplored:palm_planks":1,"minecraft:lectern":1,"regions_unexplored:cobalt_log":2,"beachparty:palm_log":2,"regions_unexplored:cypress_planks":1,"alexscaves:tesla_bulb":1,"botania:yellow_double_flower":1,"blue_skies:maple_log":2,"blue_skies:pyrope_boots":1,"vinery:apple_log":4,"regions_unexplored:ashen_sapling":1,"hexerei:mahogany_log":3,"minecraft:stone_sword":52,"minecraft:enchanting_table":1,"regions_unexplored:glister_bulb":2,"call_of_yucutan:macuahuitl":272,"blue_skies:starlit_planks":21,"minecraft:netherrack":9,"minecraft:stick":2,"minecraft:torch":575,"minecraft:anvil":1,"minecraft:wheat":1,"regions_unexplored:dead_pine_sapling":7,"alexscaves:metal_swarf":4,"regions_unexplored:clover":859,"regions_unexplored:eucalyptus_log":2,"regions_unexplored:hyssop":1,"farmersdelight:beef_patty":9,"regions_unexplored:pine_log":2,"nethers_exorcism:dna_vines":1,"regions_unexplored:daisy":3,"beachparty:palm_planks":1,"minecraft:iron_axe":2442,"blue_skies:crescent_fruit_sapling":1,"beachparty:mini_fridge":2,"minecraft:barrel":7,"minecraft:bamboo":11,"hexerei:willow_log":5,"minecraft:basalt":2,"minecraft:gunpowder":3,"minecraft:goat_horn":2,"farmersdelight:tomato_seeds":6,"hexerei:witch_hazel_fence":16,"regions_unexplored:kapok_log":3,"quark:blossom_planks":1,"regions_unexplored:dead_wood":6,"minecraft:cobbled_deepslate":84,"hexerei:herb_drying_rack":5,"quark:blossom_log":34,"minecraft:wheat_seeds":33,"minecraft:water_bucket":151,"malum:runewood_log":2,"minecraft:birch_planks":1,"regions_unexplored:dead_planks":4,"minecraft:cherry_planks":27,"regions_unexplored:brimwood_planks":1,"minecraft:cauldron":1,"minecraft:fletching_table":1,"minecraft:cracked_stone_bricks":33,"minecraft:polished_blackstone_bricks":1,"minecraft:crafting_table":11,"regions_unexplored:magnolia_shrub":1,"nethers_exorcism:indigo_planks":1,"minecraft:campfire":1,"regions_unexplored:glister_spire":1,"minecraft:diamond_pickaxe":1807,"minecraft:iron_pickaxe":528,"regions_unexplored:baobab_planks":1,"blue_skies:crescent_fruit":3,"minecraft:cobblestone":181,"blue_skies:pyrope_pickaxe":137,"minecraft:potion":2,"vinery:apple_tree_sapling":2,"quark:oak_chest":4,"minecraft:brush":130,"beachparty:rubber_ring_pelican":1,"minecraft:candle":1,"regions_unexplored:pink_lupine":5,"blue_skies:aquite_sword":525,"minecraft:cherry_sapling":14,"minecraft:moss_carpet":6,"stalwart_dungeons:iron_hammer":214,"minecraft:iron_shovel":2780,"malum:runewood_sapling":1,"hexerei:witch_hazel_sapling":7,"hexerei:witch_hazel_trapdoor":21,"minecraft:decorated_pot":5,"minecraft:shield":7,"minecraft:iron_sword":510,"doggytalents:rice_grains":13,"regions_unexplored:glistering_sprout":2,"hexerei:witch_hazel_stairs":8,"regions_unexplored:prismarite_cluster":3,"minecraft:axolotl_bucket":2,"minecraft:tuff":1,"minecraft:obsidian":11,"regions_unexplored:willow_planks":29,"minecraft:milk_bucket":2,"regions_unexplored:eucalyptus_planks":1,"minecraft:glass":8,"regions_unexplored:purple_lupine":3,"alexscaves:azure_neodymium_pillar":9,"regions_unexplored:dead_stairs":115,"blue_skies:bluebright_planks":1,"regions_unexplored:cobalt_planks":1,"farmersdelight:tomato":1,"blue_skies:lunar_stonebrick":11,"minecraft:lantern":2,"regions_unexplored:joshua_sapling":12,"blue_skies:bluebright_crafting_table":5,"minecraft:light_blue_bed":13,"hexerei:witch_hazel_slab":12,"regions_unexplored:ash_vent":1,"minecraft:item_frame":14,"minecraft:stone_bricks":418,"minecraft:magma_block":1,"minecraft:scaffolding":20,"minecraft:beetroot_seeds":11,"minecraft:gray_bed":2,"blue_skies:turquoise_stone_pickaxe":31,"regions_unexplored:socotra_log":2,"regions_unexplored:joshua_log":2,"blue_skies:bluebright_sapling":2,"minecraft:stone_pickaxe":10,"blue_skies:pyrope_axe":190,"relics:researching_table":1,"regions_unexplored:large_prismarite_cluster":1,"blue_skies:pyrope_sword":220,"minecraft:oak_planks":5,"blue_skies:starlit_sapling":1,"blue_skies:dusk_log":2,"minecraft:sugar_cane":57,"regions_unexplored:joshua_planks":963,"blue_skies:aquite_boots":1,"hexerei:mahogany_planks":1,"blue_skies:municipal_monkfish":1,"blue_skies:aquite_axe":611,"hexerei:witch_hazel_door":2,"regions_unexplored:mauve_planks":1,"minecraft:shears":150,"hexerei:willow_planks":1,"regions_unexplored:stripped_dead_wood":7,"minecraft:firework_rocket":72,"minecraft:dark_oak_log":2,"minecraft:bread":343,"regions_unexplored:kapok_planks":1,"minecraft:string":2,"blue_skies:maple_planks":1,"nethers_exorcism:indigo_log":2,"nethersdelight:hoglin_sirloin":13,"regions_unexplored:baobab_log":2,"minecraft:andesite":4,"blue_skies:turquoise_stone_axe":58,"minecraft:bone_meal":223,"minecraft:experience_bottle":7,"minecraft:cherry_boat":3,"minecraft:flint_and_steel":25,"regions_unexplored:yellow_bioshroom_stem":4,"quark:jungle_chest":2,"minecraft:cooked_chicken":5,"regions_unexplored:maple_planks":1,"malum:crude_scythe":169,"minecraft:spyglass":74,"minecraft:dirt":1066,"blue_skies:bluebright_log":2,"blue_skies:turquoise_dirt":6,"minecraft:golden_chestplate":1,"minecraft:dark_oak_planks":1,"minecraft:iron_hoe":127,"regions_unexplored:brimwood_sapling":1,"minecraft:spruce_fence":1,"blue_skies:aquite_shovel":818,"regions_unexplored:dead_slab":1,"blue_skies:zeal_lighter":2,"blue_skies:starlit_log":2,"nethers_exorcism:cooked_lurker_meat":8,"alexscaves:spelunkery_table":1,"regions_unexplored:larch_planks":1,"farmersdelight:cooked_mutton_chops":4,"blue_skies:scalefruit":3,"regions_unexplored:blue_lupine":5,"regions_unexplored:dead_pine_shrub":1,"blue_skies:dusk_planks":1,"minecraft:cooked_mutton":6,"minecraft:glass_bottle":5,"blue_skies:moonlit_bloom":1,"minecraft:baked_potato":69,"regions_unexplored:brimwood_log":2,"regions_unexplored:cypress_log":2,"minecraft:cobblestone_slab":1,"regions_unexplored:socotra_planks":1,"minecraft:painting":24,"minecraft:infested_stone_bricks":1,"minecraft:book":2,"minecraft:smoker":2,"irons_spellbooks:alchemist_cauldron":1,"regions_unexplored:palm_log":2,"minecraft:apple":2,"minecraft:map":3,"hexerei:willow_altar":5,"regions_unexplored:larch_log":5,"regions_unexplored:yellow_bioshroom_planks":3,"irons_spellbooks:scroll_forge":2,"minecraft:stone_axe":49,"regions_unexplored:flowering_sapling":1,"minecraft:white_banner":2,"regions_unexplored:dead_sapling":35,"minecraft:bucket":160,"minecraft:yellow_bed":2,"minecraft:polished_blackstone_button":1,"regions_unexplored:maple_log":2,"minecraft:splash_potion":1},"minecraft:broken":{"minecraft:golden_boots":1,"minecraft:iron_boots":3,"minecraft:iron_leggings":3,"blue_skies:aquite_boots":1,"blue_skies:pyrope_sword":1,"minecraft:iron_sword":2,"quark:forgotten_hat":3,"stalwart_dungeons:iron_hammer":1,"blue_skies:aquite_sword":1,"beachparty:rubber_ring_pelican":2,"blue_skies:pyrope_axe":1,"blue_skies:aquite_shovel":3,"minecraft:iron_axe":7,"minecraft:iron_pickaxe":2,"blue_skies:aquite_axe":2,"minecraft:iron_helmet":1,"minecraft:golden_helmet":1,"minecraft:iron_shovel":11,"blue_skies:aquite_leggings":1,"blue_skies:aquite_helmet":1,"blue_skies:pyrope_shovel":6,"blue_skies:aquite_pickaxe":2},"minecraft:killed_by":{"minecraft:piglin_brute":1,"irons_spellbooks:pyromancer":2,"minecraft:pillager":3,"minecraft:vindicator":2,"irons_spellbooks:citadel_keeper":2,"grimoireofgaia:minotaurus":1,"minecraft:zombie":6,"alexscaves:teletor":12,"blue_skies:nyctofly":2,"grimoireofgaia:succubus":1,"irons_spellbooks:summoned_skeleton":1,"blue_skies:armored_frost_spirit":1,"irons_spellbooks:apothecarist":6,"minecraft:creeper":5,"quark:forgotten":8,"minecraft:cave_spider":1,"blue_skies:emberback":5,"brazil_legends:capelobo":2,"minecraft:enderman":3,"minecraft:hoglin":2,"irons_spellbooks:necromancer":5,"alexscaves:magnetron":2,"minecraft:skeleton":5},"minecraft:custom":{"minecraft:interact_with_crafting_table":189,"minecraft:open_barrel":102,"minecraft:bell_ring":1,"minecraft:eat_cake_slice":8,"minecraft:leave_game":29,"minecraft:time_since_death":27220,"minecraft:damage_blocked_by_shield":180,"minecraft:play_time":1931230,"minecraft:deaths":96,"minecraft:jump":15465,"minecraft:enchant_item":2,"minecraft:interact_with_furnace":177,"minecraft:traded_with_villager":2,"minecraft:interact_with_cartography_table":1,"minecraft:sleep_in_bed":90,"minecraft:waystone_activated":6,"minecraft:damage_dealt":85822,"minecraft:interact_with_smoker":25,"minecraft:horse_one_cm":1692,"minecraft:use_cauldron":1,"minecraft:interact_with_smithing_table":1,"minecraft:interact_with_anvil":1,"minecraft:sneak_time":43186,"minecraft:interact_with_lectern":2,"minecraft:interact_with_blast_furnace":6,"minecraft:total_world_time":1931230,"minecraft:time_since_rest":17415,"minecraft:swim_one_cm":302925,"minecraft:fly_one_cm":3054888,"minecraft:open_chest":1436,"minecraft:fall_one_cm":421326,"minecraft:animals_bred":1,"minecraft:damage_resisted":10639,"minecraft:sprint_one_cm":3950275,"minecraft:drop":532,"minecraft:talked_to_villager":5,"minecraft:interact_with_brewingstand":2,"minecraft:walk_on_water_one_cm":1232941,"minecraft:interact_with_loom":4,"minecraft:crouch_one_cm":162595,"minecraft:mob_kills":519,"minecraft:fill_cauldron":2,"minecraft:climb_one_cm":42226,"minecraft:walk_one_cm":5390411,"minecraft:walk_under_water_one_cm":287386,"minecraft:raid_trigger":1,"minecraft:pot_flower":1,"minecraft:damage_absorbed":3515,"minecraft:damage_taken":52745,"minecraft:aviate_one_cm":1906089},"minecraft:picked_up":{"minecraft:iron_chestplate":1,"hexerei:witch_hazel_trapdoor":15,"minecraft:creeper_head":1,"minecraft:suspicious_stew":3,"regions_unexplored:magnolia_log":12,"irons_spellbooks:affinity_ring":1,"minecraft:lead":6,"regions_unexplored:glistering_sprout":21,"vinery:red_grape_seeds":3,"minecraft:oak_stairs":1,"minecraft:enchanted_book":2,"minecraft:infested_stone":24,"quark:azalea_log":4,"minecraft:music_disc_cat":1,"malum:runewood_sapling":3,"minecraft:string":51,"blue_skies:starlit_sapling":7,"minecraft:shroomlight":5,"minecraft:beetroot":3,"minecraft:cherry_boat":2,"regions_unexplored:pine_log":41,"minecraft:gold_nugget":60,"minecraft:cobbled_deepslate":498,"nethers_exorcism:indigo_roots":1,"regions_unexplored:kapok_sapling":3,"steam_powered:raw_zinc":2,"regions_unexplored:larch_log":67,"minecraft:coal_block":11,"nethers_exorcism:raw_lurker_meat":8,"blue_skies:snowcap_mushroom":3,"minecraft:sheaf_pottery_sherd":4,"hexerei:mahogany_log":79,"blue_skies:maple_sapling":11,"minecraft:big_dripleaf":7,"quark:cherry_chest":1,"minecraft:acacia_log":2,"quark:blossom_log":48,"minecraft:cherry_log":192,"blue_skies:lunar_cobblestone":3,"minecraft:cauldron":1,"regions_unexplored:socotra_log":24,"blue_skies:bluebright_crafting_table":2,"nethers_exorcism:indigo_fungus":1,"minecraft:tropical_fish":8,"minecraft:carved_pumpkin":1,"farmersdelight:rope":6,"supplementaries:ash":80,"minecraft:birch_log":5,"minecraft:magma_block":2,"minecraft:feather":4,"minecraft:water_bucket":1,"minecraft:jungle_log":15,"regions_unexplored:white_magnolia_shrub":2,"regions_unexplored:silver_birch_shrub":1,"minecraft:smoker":2,"farmersdelight:bacon":8,"regions_unexplored:dead_steppe_shrub":1,"regions_unexplored:dead_pine_shrub":2,"beachparty:palm_log":27,"minecraft:flint":7,"farmersdelight:cooked_bacon":8,"minecraft:map":1,"farmersdelight:tomato":6,"minecraft:lantern":4,"regions_unexplored:cobalt_roots":1,"hexerei:flowering_lily_pad":1,"alexscaves:galena":93,"farmersdelight:mutton_chops":6,"blue_skies:maple_log":59,"regions_unexplored:magnolia_planks":1,"malum:earthen_spirit":4,"regions_unexplored:yellow_bioshroom_stem":13,"minecraft:glowstone_dust":16,"minecraft:moss_block":69,"blue_skies:starlit_stick":2,"regions_unexplored:bamboo_log":14,"blue_skies:snowcap_pinhead":2,"botania:red_mystical_flower":4,"malum:infernal_spirit":2,"malum:raw_soulstone":2,"irons_spellbooks:legendary_ink":1,"relics:hunter_belt":3,"regions_unexplored:pine_sapling":7,"grimoireofgaia:fireshard":2,"regions_unexplored:palm_log":15,"minecraft:dark_oak_log":47,"regions_unexplored:pink_lupine":27,"minecraft:barrel":1,"regions_unexplored:brimwood_sapling":3,"regions_unexplored:glister_bulb":6,"minecraft:iron_hoe":1,"regions_unexplored:cypress_log":10,"regions_unexplored:hyssop":1,"minecraft:miner_pottery_sherd":2,"regions_unexplored:clover":2833,"botania:orange_mushroom":1,"minecraft:granite":9,"blue_skies:turquoise_stonebrick":18,"regions_unexplored:willow_log":11,"blue_skies:lunar_dirt":2,"regions_unexplored:cobalt_log":8,"regions_unexplored:baobab_log":21,"minecraft:diamond_pickaxe":4,"alexscaves:raw_scarlet_neodymium":71,"minecraft:crafting_table":2,"minecraft:shelter_pottery_sherd":4,"minecraft:coarse_dirt":1,"malum:crude_scythe":2,"minecraft:clay_ball":68,"minecraft:leather_leggings":1,"irons_spellbooks:tarnished_helmet":1,"minecraft:infested_cobblestone":29,"regions_unexplored:blue_bioshroom":1,"blue_skies:bluebright_sapling":7,"nethers_exorcism:indigo_leaves":5,"regions_unexplored:dead_log":259,"regions_unexplored:poppy_bush":9,"minecraft:netherite_scrap":1,"regions_unexplored:dead_sapling":80,"minecraft:iron_shovel":1,"minecraft:cracked_stone_bricks":2,"farmersdelight:beef_patty":10,"minecraft:beef":2,"betterarcheology:cracked_mud_bricks":2,"minecraft:jungle_sapling":3,"minecraft:iron_nugget":53,"minecraft:birch_sapling":3,"quark:yellow_blossom_sapling":5,"regions_unexplored:glister_spire":2,"minecraft:chest":3,"minecraft:egg":4,"blue_skies:moonlit_water_lily":11,"minecraft:stone":31,"nethers_exorcism:dna_vines":18,"minecraft:raw_gold_block":10,"farmersdelight:minced_beef":10,"minecraft:spruce_fence":1,"farmersdelight:tomato_seeds":11,"minecraft:skull_pottery_sherd":1,"botania:pink_mushroom":2,"minecraft:carrot":43,"minecraft:redstone":45,"hexerei:witch_hazel_fence":2,"regions_unexplored:kapok_log":19,"malum:blazing_quartz":5,"regions_unexplored:dead_pine_sapling":10,"minecraft:tnt":1,"irons_spellbooks:gold_spell_book":1,"blue_skies:briskbloom":2,"regions_unexplored:mauve_sapling":4,"minecraft:beetroot_seeds":16,"regions_unexplored:joshua_log":356,"minecraft:decorated_pot":2,"regions_unexplored:felicia_daisy":2,"minecraft:hay_block":127,"minecraft:gold_ingot":6,"regions_unexplored:purple_lupine":33,"minecraft:glow_berries":5,"blue_skies:moonstone_shard":97,"minecraft:mutton":4,"minecraft:white_wool":28,"minecraft:bone_block":33,"regions_unexplored:eucalyptus_log":53,"minecraft:tripwire_hook":1,"malum:cluster_of_brilliance":9,"minecraft:filled_map":4,"doggytalents:rice_grains":22,"minecraft:packed_mud":1,"minecraft:oak_log":23,"regions_unexplored:red_maple_sapling":3,"minecraft:golden_boots":1,"botania:red_mushroom":1,"malum:exposed_runewood_log":2,"minecraft:white_banner":3,"minecraft:apple":18,"minecraft:stone_bricks":74,"regions_unexplored:glistering_ivy":2,"blue_skies:pyrope_gem":22,"minecraft:spore_blossom":1,"minecraft:cobweb":17,"minecraft:blade_pottery_sherd":1,"regions_unexplored:larch_sapling":18,"relics:infinity_ham":2,"beachparty:overgrown_disc":1,"regions_unexplored:brimwood_log":32,"minecraft:glass_bottle":1,"minecraft:gray_bed":3,"minecraft:iron_sword":2,"minecraft:flowering_azalea":2,"blue_skies:stripped_starlit_log":1,"minecraft:smooth_basalt":5,"blue_skies:crescent_fruit_sapling":11,"beachparty:palm_sapling":7,"blue_skies:turquoise_dirt":6,"minecraft:spyglass":1,"minecraft:gravel":24,"hexerei:witch_hazel_stairs":2,"minecraft:prize_pottery_sherd":1,"blue_skies:bluebright_log":30,"irons_spellbooks:scroll_forge":1,"minecraft:crying_obsidian":4,"blue_skies:starlit_log":36,"minecraft:leather_helmet":1,"blue_skies:raw_aquite":14,"minecraft:infested_stone_bricks":43,"regions_unexplored:cave_hyssop":1,"minecraft:slime_ball":12,"minecraft:snort_pottery_sherd":2,"regions_unexplored:fireweed":4,"betterarcheology:growth_totem":1,"minecraft:painting":27,"alexscaves:scarlet_neodymium_pillar":45,"minecraft:baked_potato":1,"minecraft:melon_seeds":8,"minecraft:ender_pearl":4,"irons_spellbooks:scroll":2,"minecraft:wheat":42,"alexscaves:cave_tablet":6,"minecraft:potion":1,"malum:grim_talc":4,"regions_unexplored:magnolia_shrub":1,"regions_unexplored:prismarite_cluster":22,"irons_spellbooks:nature_rune":1,"minecraft:raw_copper":49,"minecraft:experience_bottle":3,"irons_spellbooks:arcane_essence":16,"regions_unexplored:ashen_sapling":1,"minecraft:cobblestone_slab":5,"blue_skies:bug_guts":9,"minecraft:calcite":3,"minecraft:azalea":1,"minecraft:iron_pickaxe":1,"irons_spellbooks:inscription_table":3,"farmersdelight:cabbage_seeds":5,"minecraft:iron_boots":2,"minecraft:furnace":7,"blue_skies:dusk_log":27,"minecraft:stick":595,"regions_unexplored:yellow_bioshroom_planks":1,"alexscaves:tesla_bulb":1,"minecraft:oak_fence":4,"minecraft:torch":286,"alexscaves:raw_azure_neodymium":51,"regions_unexplored:pink_magnolia_shrub":1,"regions_unexplored:daisy":5,"hexerei:witch_hazel_slab":4,"hexerei:stripped_willow_log":3,"regions_unexplored:barley":6,"blue_skies:maple_stick":5,"minecraft:rotten_flesh":272,"goblins_tyranny:shaman_skull":4,"blue_skies:pyrope_sword":1,"regions_unexplored:ashen_log":20,"regions_unexplored:mauve_log":12,"blue_skies:warding_pearl":1,"hexerei:herb_drying_rack":6,"minecraft:obsidian":25,"irons_spellbooks:cooldown_ring":2,"vinery:apple_log":44,"minecraft:cobblestone":1196,"relics:roller_skates":1,"blue_skies:crescent_fruit":23,"minecraft:cherry_planks":4,"minecraft:andesite":157,"blue_skies:brewberry":5,"regions_unexplored:cherry_shrub":2,"minecraft:potato":74,"baedoorlib:nether_soul_essence":2,"minecraft:tuff":22,"supplementaries:flax_seeds":10,"minecraft:lapis_lazuli":38,"minecraft:dirt":4663,"minecraft:name_tag":4,"irons_spellbooks:hogskin":7,"minecraft:bone":95,"minecraft:bow":12,"minecraft:wheat_seeds":107,"minecraft:orange_tulip":1,"minecraft:raw_gold":74,"regions_unexplored:baobab_sapling":4,"minecraft:grindstone":1,"minecraft:mossy_stone_bricks":3,"minecraft:fletching_table":1,"minecraft:bamboo":139,"minecraft:oak_planks":5,"botania:gray_mystical_flower":4,"malum:wicked_spirit":2,"regions_unexplored:palm_sapling":1,"minecraft:music_disc_13":2,"botania:yellow_double_flower":1,"blue_skies:brumble":1,"regions_unexplored:joshua_sapling":14,"betterarcheology:evoker_trap":1,"betterarcheology:artifact_shards":2,"minecraft:sand":8,"hexerei:willow_log":21,"minecraft:grass_block":2,"farmersdelight:cooked_mutton_chops":4,"minecraft:mossy_cobblestone":17,"regions_unexplored:cattail":6,"nethers_exorcism:indigo_fruit_food":4,"beachparty:rubber_ring_pelican":1,"minecraft:sugar":8,"minecraft:diamond":11,"minecraft:polished_blackstone_button":1,"regions_unexplored:brimwood_leaves":149,"minecraft:crossbow":1,"minecraft:bone_meal":26,"regions_unexplored:socotra_shrub":2,"minecraft:emerald":47,"minecraft:oak_sapling":5,"minecraft:netherrack":30,"nethersdelight:hoglin_loin":13,"minecraft:cocoa_beans":6,"minecraft:allium":2,"regions_unexplored:mycotoxic_grass":2,"grimoireofgaia:soulfire":1,"blue_skies:star_flare":3,"minecraft:chicken":1,"minecraft:packed_ice":2,"minecraft:wooden_pickaxe":1,"blue_skies:glimmer_reed":142,"doggytalents:rice_wheat":6,"blue_skies:umber":4,"minecraft:chain":11,"beachparty:coconut":5,"minecraft:brick":1,"blue_skies:municipal_monkfish":1,"alexscaves:metal_swarf":63,"minecraft:moss_carpet":9,"minecraft:iron_axe":2,"regions_unexplored:spruce_shrub":1,"betterarcheology:sheep_fossil_body":3,"minecraft:item_frame":17,"minecraft:blackstone":70,"regions_unexplored:cobalt_sapling":3,"regions_unexplored:duskmelon_slice":2,"minecraft:candle":55,"vinery:apple_tree_sapling":18,"irons_spellbooks:epic_ink":1,"minecraft:player_head":2,"hexerei:mahogany_sapling":20,"minecraft:sugar_cane":183,"hexerei:willow_altar":4,"nethers_exorcism:indigo_log":35,"minecraft:dark_oak_sapling":9,"minecraft:raw_iron":224,"grimoireofgaia:meat":2,"regions_unexplored:ash_vent":18,"minecraft:copper_ingot":2,"botania:mana_bottle":1,"minecraft:bowl":2,"botania:green_mushroom":1,"regions_unexplored:blue_lupine":31,"minecraft:polished_blackstone_bricks":1,"regions_unexplored:dead_slab":1,"minecraft:stone_button":8,"minecraft:light_blue_bed":13,"minecraft:iron_horse_armor":4,"hexerei:sage_seed":16,"blue_skies:moonlit_bloom":1,"minecraft:arrow":95,"regions_unexplored:maple_sapling":1,"malum:natural_quartz":20,"alexscaves:spelunkery_table":2,"hexerei:witch_hazel_sapling":7,"malum:rotting_essence":3,"regions_unexplored:stripped_dead_wood":7,"hexerei:book_of_shadows":3,"minecraft:skeleton_skull":3,"regions_unexplored:glistering_fern":2,"minecraft:basalt":74,"regions_unexplored:hanging_prismarite":6,"minecraft:glow_ink_sac":14,"minecraft:salmon":1,"regions_unexplored:joshua_planks":454,"minecraft:leather":32,"minecraft:ice":7,"alexscaves:heavyweight":3,"regions_unexplored:dead_stairs":10,"blue_skies:turquoise_cobblestone":180,"minecraft:yellow_bed":2,"malum:runewood_log":89,"blue_skies:lunar_stick":8,"minecraft:gunpowder":16,"regions_unexplored:salmon_poppy_bush":24,"alexscaves:ferrouslime_ball":2,"minecraft:heart_pottery_sherd":4,"malum:cthonic_gold_fragment":41,"quark:forgotten_hat":3,"irons_spellbooks:rare_ink":1,"minecraft:cooked_mutton":1,"regions_unexplored:large_prismarite_cluster":5,"blue_skies:aquite_axe":3,"blue_skies:lunar_stonebrick":13,"minecraft:iron_ingot":20,"minecraft:cooked_chicken":5,"beachparty:mini_fridge":1,"regions_unexplored:stripped_dead_log":109,"irons_spellbooks:cinder_essence":2,"regions_unexplored:yellow_bioshroom":19,"regions_unexplored:yellow_lupine":1,"minecraft:book":66,"minecraft:scaffolding":1,"regions_unexplored:eucalyptus_sapling":9,"minecraft:brush":1,"minecraft:quartz":1,"hexerei:witch_hazel_log":29,"minecraft:amethyst_shard":10,"blue_skies:fiery_bean_seeds":2,"hexerei:willow_sapling":4,"minecraft:spider_eye":6,"blue_skies:monitor_tail":4,"blue_skies:aquite_sword":3,"blue_skies:starlit_planks":2,"minecraft:pumpkin_seeds":3,"steam_powered:raw_tin":9,"regions_unexplored:silver_birch_log":28,"minecraft:iron_helmet":1,"minecraft:cherry_sapling":115,"regions_unexplored:maple_log":19,"alexscaves:azure_neodymium_pillar":50,"blue_skies:bluebright_stick":2,"minecraft:coal":248}},"DataVersion":3465}